mp3lyrics/__init__.py
mp3lyrics/api_config.py
mp3lyrics/mp3lyrics.py
mp3lyrics-0.1.0.dist-info/LICENSE
mp3lyrics-0.1.0.dist-info/METADATA
mp3lyrics-0.1.0.dist-info/WHEEL
mp3lyrics-0.1.0.dist-info/entry_points.txt
mp3lyrics-0.1.0.dist-info/top_level.txt
mp3lyrics-0.1.0.dist-info/RECORD
