Metadata-Version: 2.1
Name: mp3lyrics
Version: 0.1.0
Summary: Fetch lyrics from Genius and embed into MP3 metadata
Author: Odhran McElhinney
Author-email: odhranmcelhinney@hotmail.com
Classifier: Programming Language :: Python :: 3
License-File: LICENSE
Requires-Dist: requests
Requires-Dist: html2text
Requires-Dist: eyed3
Requires-Dist: fuzzywuzzy
Requires-Dist: python-Levenshtein
Requires-Dist: alive-progress
